veloAdmin/__init__.py
veloAdmin/create.py
veloadmin-1.0.2.dist-info/METADATA
veloadmin-1.0.2.dist-info/WHEEL
veloadmin-1.0.2.dist-info/entry_points.txt
veloadmin-1.0.2.dist-info/top_level.txt
veloadmin-1.0.2.dist-info/RECORD
