Metadata-Version: 2.1
Name: veloadmin
Version: 1.0.2
Summary: VeloAdmin is tool design to handle veloweb server
Author: Pawan kumar
Author-email: control@vvfin.in
Requires-Dist: veloweb
